{"title":"Mr.ju's_bog","uid":"188cad95d160e1126e3df15b31bcb8de","slug":"hello-world","date":"2022-11-09T08:11:05.870Z","updated":"2022-11-09T10:59:55.503Z","comments":true,"path":"api/articles/hello-world.json","keywords":"Semiconductor, computer, automation","cover":null,"content":"<p>Welcome to Mr.ju’s_bog. Here you will walk into Mrju’s inner world and roam in his world. He will share his graduate studies from time to time. Let’s get started</p>\n<h2 id=\"Quick-Start\"><a href=\"#Quick-Start\" class=\"headerlink\" title=\"Quick Start\"></a>Quick Start</h2><h3 id=\"Create-a-new-post\"><a href=\"#Create-a-new-post\" class=\"headerlink\" title=\"Create a new post\"></a>Create a new post</h3><pre class=\"line-numbers language-bash\" data-language=\"bash\"><code class=\"language-bash\">$ hexo new <span class=\"token string\">\"My New Post\"</span><span aria-hidden=\"true\" class=\"line-numbers-rows\"><span></span></span></code></pre>\n\n<p>More info: <a href=\"https://hexo.io/docs/writing.html\">Writing</a></p>\n<h3 id=\"Run-server\"><a href=\"#Run-server\" class=\"headerlink\" title=\"Run server\"></a>Run server</h3><pre class=\"line-numbers language-bash\" data-language=\"bash\"><code class=\"language-bash\">$ hexo server<span aria-hidden=\"true\" class=\"line-numbers-rows\"><span></span></span></code></pre>\n\n<p>More info: <a href=\"https://hexo.io/docs/server.html\">Server</a></p>\n<h3 id=\"Generate-static-files\"><a href=\"#Generate-static-files\" class=\"headerlink\" title=\"Generate static files\"></a>Generate static files</h3><pre class=\"line-numbers language-bash\" data-language=\"bash\"><code class=\"language-bash\">$ hexo generate<span aria-hidden=\"true\" class=\"line-numbers-rows\"><span></span></span></code></pre>\n\n<p>More info: <a href=\"https://hexo.io/docs/generating.html\">Generating</a></p>\n<h3 id=\"Deploy-to-remote-sites\"><a href=\"#Deploy-to-remote-sites\" class=\"headerlink\" title=\"Deploy to remote sites\"></a>Deploy to remote sites</h3><pre class=\"line-numbers language-bash\" data-language=\"bash\"><code class=\"language-bash\">$ hexo deploy<span aria-hidden=\"true\" class=\"line-numbers-rows\"><span></span></span></code></pre>\n\n<p>More info: <a href=\"https://hexo.io/docs/one-command-deployment.html\">Deployment</a></p>\n","text":"Welcome to Mr.ju’s_bog. Here you will walk into Mrju’s inner world and roam in his world. He will share his graduate studies from time to ti...","link":"","photos":[],"count_time":{"symbolsCount":397,"symbolsTime":"1 mins."},"categories":[],"tags":[],"toc":"<ol class=\"toc\"><li class=\"toc-item toc-level-2\"><a class=\"toc-link\" href=\"#Quick-Start\"><span class=\"toc-text\">Quick Start</span></a><ol class=\"toc-child\"><li class=\"toc-item toc-level-3\"><a class=\"toc-link\" href=\"#Create-a-new-post\"><span class=\"toc-text\">Create a new post</span></a></li><li class=\"toc-item toc-level-3\"><a class=\"toc-link\" href=\"#Run-server\"><span class=\"toc-text\">Run server</span></a></li><li class=\"toc-item toc-level-3\"><a class=\"toc-link\" href=\"#Generate-static-files\"><span class=\"toc-text\">Generate static files</span></a></li><li class=\"toc-item toc-level-3\"><a class=\"toc-link\" href=\"#Deploy-to-remote-sites\"><span class=\"toc-text\">Deploy to remote sites</span></a></li></ol></li></ol>","author":{"name":"Mr.ju","slug":"blog-author","avatar":"https://img-blog.csdnimg.cn/20210313122054101.png","link":"我是大帅哥","description":"I'm a millionaire","socials":{"github":"","twitter":"","stackoverflow":"","wechat":"","qq":"","weibo":"","zhihu":"","csdn":"","juejin":"","customs":{}}},"mapped":true,"prev_post":{},"next_post":{}}